bubba/__init__.py
bubba/api.py
bubba/middleware.py
bubba/orm.py
bubba/response.py
bubba-0.0.3.dist-info/METADATA
bubba-0.0.3.dist-info/WHEEL
bubba-0.0.3.dist-info/top_level.txt
bubba-0.0.3.dist-info/RECORD
