Metadata-Version: 2.1
Name: bubba
Version: 0.0.3
Summary: Bubba Python Web Framework the simplest framework.
Author: Oscar Carrillo
Author-email: oscara1706cl@gmail.com
License: MIT
Classifier: Programming Language :: Python :: 3.6
Requires-Python: >=3.6.0
Requires-Dist: Jinja2 (==3.1.2)
Requires-Dist: parse (==1.19.0)
Requires-Dist: requests (==2.28.1)
Requires-Dist: requests-wsgi-adapter (==0.4.1)
Requires-Dist: WebOb (==1.8.7)
Requires-Dist: whitenoise (==6.2.0)
